fast_tmfg/TMFG_core.py
fast_tmfg/__init__.py
fast_tmfg/utils.py
fast_tmfg-0.0.12.dist-info/METADATA
fast_tmfg-0.0.12.dist-info/WHEEL
fast_tmfg-0.0.12.dist-info/top_level.txt
fast_tmfg-0.0.12.dist-info/RECORD
