Metadata-Version: 2.1
Name: fast_tmfg
Version: 0.0.12
Summary: The official package to compute the Triangulated Maximally Filtered Graph (TMFG).
Home-page: https://github.com/FinancialComputingUCL/Triangulated_Maximally_Filtered_Graph
Author: Antonio Briola
Author-email: anto.briola96@gmail.com
Classifier: Programming Language :: Python :: 3
Classifier: License :: OSI Approved :: MIT License
Classifier: Operating System :: OS Independent
Requires-Python: >=3.7
Requires-Dist: numpy
Requires-Dist: pandas
Requires-Dist: networkx
